[{"id":"c0d74936.badd98","type":"tab","label":"Life Expectancy Prediction","disabled":false,"info":""},{"id":"b50d34d0.d8a6d8","type":"ui_form","z":"c0d74936.badd98","name":"","label":"","group":"4f575e1c.8f0c1","order":0,"width":0,"height":0,"options":[{"label":"Adult Mortality","value":"am","type":"number","required":true,"rows":null},{"label":"Percentage Expenditure","value":"pe","type":"number","required":true,"rows":null},{"label":"Body Mass Index","value":"bmi","type":"number","required":true,"rows":null},{"label":"HIV/AIDS","value":"hivaids","type":"number","required":true,"rows":null},{"label":"GDP","value":"gdp","type":"number","required":true,"rows":null},{"label":"Income Composition of Resources","value":"incop","type":"number","required":true,"rows":null},{"label":"Schooling","value":"schl","type":"number","required":true,"rows":null}],"formValue":{"am":"","pe":"","bmi":"","hivaids":"","gdp":"","incop":"","schl":""},"payload":"","submit":"Submit","cancel":"Clear","topic":"","x":110,"y":400,"wires":[["4a0f0e39.e96e4"]]},{"id":"4a0f0e39.e96e4","type":"function","z":"c0d74936.badd98","name":"pre token","func":"//make user given values as global variables\nglobal.set(\"am\",msg.payload.am);\nglobal.set(\"pe\",msg.payload.pe);\nglobal.set(\"bmi\",msg.payload.bmi);\nglobal.set(\"hivaids\",msg.payload.hivaids);\nglobal.set(\"gdp\",msg.payload.gdp);\nglobal.set(\"incop\",msg.payload.incop);\nglobal.set(\"schl\",msg.payload.schl);\n\n//following are required to receive a token\nvar apikey=\"dD5A7DumNSeO_UOjvMs45iIOQCrC47NBDFroK25SuSjc\";\nmsg.headers={\"content-type\":\"application/x-www-form-urlencoded\"};\nmsg.payload={\"grant_type\":\"urn:ibm:params:oauth:grant-type:apikey\",\"apikey\":apikey};\nreturn msg;\n","outputs":1,"noerr":0,"initialize":"","finalize":"","x":280,"y":280,"wires":[["e0c215ab.314598"]]},{"id":"b224de9a.9b12e","type":"http request","z":"c0d74936.badd98","name":"","method":"POST","ret":"obj","paytoqs":"ignore","url":"https://eu-gb.ml.cloud.ibm.com/v3/wml_instances/b2f4bd86-c4d1-4756-92de-b9f48c5d475c/deployments/20c9cf1f-a5cd-4c21-8538-52e17c3b213b/online","tls":"","persist":false,"proxy":"","authType":"","x":850,"y":280,"wires":[["f933dec4.bdcb6","26365853.723548"]]},{"id":"bd5eb48b.2cd168","type":"debug","z":"c0d74936.badd98","name":"","active":true,"tosidebar":true,"console":false,"tostatus":false,"complete":"false","x":1270,"y":160,"wires":[]},{"id":"26365853.723548","type":"function","z":"c0d74936.badd98","name":"getFrom Endpoint","func":"msg.payload=msg.payload.values[0][0];\nreturn msg;","outputs":1,"noerr":0,"initialize":"","finalize":"","x":1070,"y":220,"wires":[["fd8051a2.77804","bd5eb48b.2cd168"]]},{"id":"f933dec4.bdcb6","type":"debug","z":"c0d74936.badd98","name":"","active":true,"tosidebar":true,"console":false,"tostatus":false,"complete":"payload","targetType":"msg","statusVal":"","statusType":"auto","x":1070,"y":360,"wires":[]},{"id":"cc78d227.2dfd4","type":"function","z":"c0d74936.badd98","name":"sendTo Endpoint","func":"//get token and make headers\nvar token=msg.payload.access_token;\nvar instance_id=\"b2f4bd86-c4d1-4756-92de-b9f48c5d475c\"\nmsg.headers={'Content-Type': 'application/json',\"Authorization\":\"Bearer \"+token,\"ML-Instance-ID\":instance_id}\n\n//get variables that are set earlier\nvar am = global.get(\"am\");\nvar pe = global.get(\"pe\");\nvar bmi = global.get(\"bmi\");\nvar hivaids = global.get(\"hivaids\");\nvar gdp = global.get(\"gdp\");\nvar incop = global.get(\"incop\");\nvar schl = global.get(\"schl\");\n\n//send the user values to service endpoint\nmsg.payload = \n{\"fields\":[\"Adult Mortality\", \"percentage expenditure\", \" BMI \", \" HIV/AIDS\", \"GDP\", \"Income composition of resources\", \"Schooling\"],\n\"values\":[[am,pe,bmi,hivaids,gdp,incop,schl]]};\n\nreturn msg;\n","outputs":1,"noerr":0,"initialize":"","finalize":"","x":650,"y":280,"wires":[["b224de9a.9b12e"]]},{"id":"e0c215ab.314598","type":"http request","z":"c0d74936.badd98","name":"","method":"POST","ret":"obj","paytoqs":"ignore","url":"https://iam.cloud.ibm.com/identity/token","tls":"","persist":false,"proxy":"","authType":"basic","x":450,"y":280,"wires":[["cc78d227.2dfd4"]]},{"id":"fd8051a2.77804","type":"ui_text","z":"c0d74936.badd98","group":"4f575e1c.8f0c1","order":1,"width":0,"height":0,"name":"","label":"Life Prediction","format":"{{msg.payload}}","layout":"row-spread","x":1280,"y":280,"wires":[]},{"id":"4f575e1c.8f0c1","type":"ui_group","z":"","name":"Life Expectancy Prediction","tab":"e39baf24.56317","order":1,"disp":true,"width":"6","collapse":false},{"id":"e39baf24.56317","type":"ui_tab","z":"","name":"Home Page","icon":"dashboard","disabled":false,"hidden":false}]